selm_lammps.libs/libexpat-aad7388c.so.1.6.2
selm_lammps.libs/libz-7fd423a0.so.1.2.8
selm_lammps.libs/libfftw3-f0a5c1ad.so.3.5.5
selm_lammps.libs/libvtkIOXML-6-5d8d7fb9.3.so.6.3.0
selm_lammps.libs/libvtkCommonSystem-6-18a6fd62.3.so.6.3.0
selm_lammps.libs/libvtkIOLegacy-6-92a4f5d3.3.so.6.3.0
selm_lammps.libs/libvtkIOParallelXML-6-05c09d77.3.so.6.3.0
selm_lammps.libs/libvtkIOXMLParser-6-92ca0d92.3.so.6.3.0
selm_lammps.libs/libvtkCommonMath-6-58645a13.3.so.6.3.0
selm_lammps.libs/libselm-5d3fe326.so
selm_lammps.libs/libvtkCommonMisc-6-7d806739.3.so.6.3.0
selm_lammps.libs/libvtksys-6-a35631b8.3.so.6.3.0
selm_lammps.libs/libvtkCommonCore-6-32d822e3.3.so.6.3.0
selm_lammps.libs/libjpeg-0784ef09.so.62.2.0
selm_lammps.libs/libvtkIOCore-6-80b1ed48.3.so.6.3.0
selm_lammps.libs/libvtkCommonDataModel-6-e27c45b4.3.so.6.3.0
selm_lammps.libs/libvtkParallelCore-6-5cfbdae9.3.so.6.3.0
selm_lammps.libs/libvtkCommonExecutionModel-6-623b61c0.3.so.6.3.0
selm_lammps.libs/libpng16-121b9de7.so.16.28.0
selm_lammps.libs/libvtkCommonTransforms-6-9fb2c644.3.so.6.3.0
selm_lammps/lammps.py
selm_lammps/__init__.py
selm_lammps/liblammps.so
selm_lammps/util.py
selm_lammps/tests/t1.py
selm_lammps/tests/__init__.py
selm_lammps/examples/__init__.py
selm_lammps/examples/test1.py
selm_lammps-0.2.19.dev0.dist-info/RECORD
selm_lammps-0.2.19.dev0.dist-info/top_level.txt
selm_lammps-0.2.19.dev0.dist-info/METADATA
selm_lammps-0.2.19.dev0.dist-info/LICENSE
selm_lammps-0.2.19.dev0.dist-info/WHEEL
