Metadata-Version: 2.1
Name: selm-lammps
Version: 0.2.19.dev0
Summary: SELM-LAMMPS package for pre-compiled binaries with python interface.  For more information, see http://mango-selm.org
Home-page: UNKNOWN
Author: UNKNOWN
Author-email: UNKNOWN
License: UNKNOWN
Platform: UNKNOWN
Requires-Dist: numpy
Requires-Dist: matplotlib
